pyThermoFlash/__init__.py
pyThermoFlash/app.py
pyThermoFlash/config/__init__.py
pyThermoFlash/config/constants.py
pyThermoFlash/config/setting.py
pyThermoFlash/core/__init__.py
pyThermoFlash/core/main.py
pyThermoFlash/data/__init__.py
pyThermoFlash/docs/__init__.py
pyThermoFlash/docs/activity.py
pyThermoFlash/docs/equilibria.py
pyThermoFlash/docs/source.py
pyThermoFlash/docs/vle.py
pyThermoFlash/models/__init__.py
pyThermoFlash/models/flash.py
pyThermoFlash/utils/__init__.py
pyThermoFlash/utils/component_utils.py
pyThermoFlash/utils/display.py
pyThermoFlash/utils/result_manager.py
pyThermoFlash/utils/tools.py
pythermoflash-0.2.3.dist-info/licenses/LICENSE
pythermoflash-0.2.3.dist-info/METADATA
pythermoflash-0.2.3.dist-info/WHEEL
pythermoflash-0.2.3.dist-info/top_level.txt
pythermoflash-0.2.3.dist-info/RECORD
