Metadata-Version: 2.4
Name: pyThermoFlash
Version: 0.2.3
Summary: PyThermoFlash is a powerful and user-friendly computational tool tailored for engineers, researchers, and scientists working with thermodynamic systems. It specializes in performing bubble-point, dew-point, and flash calculations, which are essential for determining the equilibrium state of mixtures under specified conditions. With support for various thermodynamic models, PyThermoFlash ensures accurate predictions of phase behavior and properties for complex fluid systems.
Author: Sina Gilassi
Author-email: Sina Gilassi <sina.gilassi@gmail.com>
License-Expression: MIT
Project-URL: Homepage, https://github.com/sinagilassi/PyThermoFlash
Project-URL: Documentation, https://pythermoflash.readthedocs.io/en/latest/
Project-URL: Source, https://github.com/sinagilassi/PyThermoFlash
Project-URL: Tracker, https://github.com/sinagilassi/PyThermoFlash/issues
Keywords: chemical-engineering,equation-of-state,thermodynamics,thermodynamic-models,flash-calculations,equilibrium,vle-calculations,raoult-law,phase-equilibrium,dew-point-calculation,bubble-point-calculation,vapor-liquid-equilibrium,NRTL,UNIQUAC,SRK,PR,RK,vdW
Classifier: Development Status :: 1 - Planning
Classifier: Intended Audience :: Education
Classifier: Programming Language :: Python :: 3.11
Classifier: Operating System :: Unix
Classifier: Operating System :: MacOS :: MacOS X
Classifier: Operating System :: Microsoft :: Windows
Requires-Python: >=3.10
License-File: LICENSE
Requires-Dist: numpy>=2.3.5
Requires-Dist: scipy>=1.16.3
Requires-Dist: pydantic>=2.12.4
Requires-Dist: pydantic-settings>=2.12.0
Requires-Dist: pycuc
Requires-Dist: pythermodb
Requires-Dist: pythermodb-settings
Requires-Dist: pythermolinkdb
Requires-Dist: pythermomodels
Provides-Extra: dev
Requires-Dist: psutil>=7.1.3; extra == "dev"
Dynamic: author
Dynamic: license-file
Dynamic: requires-python
